chatgpterminal/conversation.py
chatgpterminal/main.py
chatgpterminal/message.py
chatgpterminal/sys_dialogue/help.txt
chatgpterminal/sys_dialogue/model.txt
chatgpterminal-0.1.6.dist-info/METADATA
chatgpterminal-0.1.6.dist-info/WHEEL
chatgpterminal-0.1.6.dist-info/entry_points.txt
chatgpterminal-0.1.6.dist-info/RECORD
