Metadata-Version: 2.1
Name: chatgpterminal
Version: 0.1.6
Summary: 
Author: Artur Dernst
Author-email: artur.dernst@gmail.com
Requires-Python: >=3.10,<4.0
Classifier: Programming Language :: Python :: 3
Classifier: Programming Language :: Python :: 3.10
Classifier: Programming Language :: Python :: 3.11
Classifier: Programming Language :: Python :: 3.12
Requires-Dist: colorama (>=0.4.6,<0.5.0)
Requires-Dist: openai (==0.27.8)
Requires-Dist: pygments (>=2.17.2,<3.0.0)
